advbox/__init__.py
advbox/adversary.py
advbox/attacks/__init__.py
advbox/attacks/base.py
advbox/attacks/cw.py
advbox/attacks/deepfool.py
advbox/attacks/gradient_method.py
advbox/attacks/lbfgs.py
advbox/attacks/localsearch.py
advbox/attacks/saliency.py
advbox/attacks/tf/__init__.py
advbox/attacks/tf/tools.py
advbox/defences/__init__.py
advbox/defences/feature_squeezing.py
advbox/defences/gaussian_augmentation.py
advbox/defences/label_smoothing.py
advbox/defences/spatial_smoothing.py
advbox/models/__init__.py
advbox/models/base.py
advbox/models/graphpipeBlackBox.py
advbox/models/keras.py
advbox/models/mxnet.py
advbox/models/paddle.py
advbox/models/paddleBlackBox.py
advbox/models/paddleFeatureFqueezingDefence.py
advbox/models/paddleLabelSmoothingDefence.py
advbox/models/paddleSpatialSmoothingDefence.py
advbox/models/pytorch.py
advbox/models/tensorflow.py
advbox-0.4.1.dist-info/METADATA
advbox-0.4.1.dist-info/RECORD
advbox-0.4.1.dist-info/WHEEL
advbox-0.4.1.dist-info/top_level.txt
tutorials/__init__.py
tutorials/cifar10_model.py
tutorials/cifar10_tutorial_bim.py
tutorials/cifar10_tutorial_deepfool.py
tutorials/cifar10_tutorial_fgsm.py
tutorials/cifar10_tutorial_jsma.py
tutorials/cifar10_tutorial_singlepixelattack.py
tutorials/imagenet_tools_mxnet.py
tutorials/imagenet_tools_pytorch.py
tutorials/imagenet_tutorial_deepfool_k.py
tutorials/imagenet_tutorial_deepfool_tf.py
tutorials/imagenet_tutorial_fgsm_k.py
tutorials/imagenet_tutorial_fgsm_mxnet.py
tutorials/imagenet_tutorial_fgsm_pytorch.py
tutorials/imagenet_tutorial_fgsm_tf.py
tutorials/imagenet_tutorial_localsearchattack.py
tutorials/imagenet_tutorial_singlepixelattack.py
tutorials/keras_demo.py
tutorials/mnist_model.py
tutorials/mnist_model_gaussian_augmentation_defence.py
tutorials/mnist_model_pytorch.py
tutorials/mnist_tutorial_bim.py
tutorials/mnist_tutorial_caffe_fgsm.py
tutorials/mnist_tutorial_deepfool.py
tutorials/mnist_tutorial_defences_feature_squeezing.py
tutorials/mnist_tutorial_defences_gaussian_augmentation.py
tutorials/mnist_tutorial_defences_label_smoothing.py
